airs/core/models/__init__.py
airs/core/models/mapper.py
airs/core/models/model.py
airsmodel-0.10.6.dist-info/METADATA
airsmodel-0.10.6.dist-info/WHEEL
airsmodel-0.10.6.dist-info/top_level.txt
airsmodel-0.10.6.dist-info/RECORD
