Metadata-Version: 2.1
Name: airsmodel
Version: 0.10.6
Summary: ARLAS Item Registration Service Model
Home-page: UNKNOWN
Author: Gisaïa
License: UNKNOWN
Platform: UNKNOWN
Requires-Python: >=3.10
